{
  "drum_map": {
    "C1": "Kick 1 (Acoustic)",
    "C#1": "Kick 2 (Rimshot)",
    "D1": "Snare 1 (Acoustic)",
    "D#1": "Snare 2 (Rimshot)",
    "E1": "Snare 3 (Side Stick)",
    "F#1": "Hi-Hat Closed",
    "G#1": "Hi-Hat Pedal",
    "A#1": "Hi-Hat Open",
    "C2": "Crash 1",
    "C#2": "Crash 2",
    "D2": "Ride 1",
    "D#2": "Ride 2 (Bell)",
    "E2": "Ride 3 (Edge)",
    "F2": "Tom 1 (High)",
    "F#2": "Tom 2 (High-Mid)",
    "G2": "Tom 3 (Low-Mid)",
    "G#2": "Tom 4 (Low)",
    "A2": "Tom 5 (Floor)",
    "A#2": "Tom 6 (Floor)",
    "B2": "Tambourine",
    "C3": "Shaker",
    "C#3": "Cowbell",
    "D3": "Triangle",
    "D#3": "Wood Block",
    "E3": "Clap",
    "F3": "Snap"
  },
  "drum_notes": {
    "kick": 36,
    "snare": 38,
    "hihat_closed": 42,
    "hihat_open": 46,
    "crash": 49,
    "ride": 51,
    "tom_high": 48,
    "tom_mid": 47,
    "tom_low": 43
  },
  "description": "General MIDI (GM) Standard Drum Map",
  "note": "Channel 9 is reserved for percussion in General MIDI standard"
}